{
  "_class": "shapeGroup",
  "clippingMaskMode": 0,
  "do_objectID": "AEA74D27-F0C5-48B0-8CE9-B1289463E74D",
  "exportOptions": {
    "_class": "exportOptions",
    "do_objectID": "85A8A4E9-9C40-4ACF-9590-4FC50C137114",
    "exportFormats": [
    ],
    "includedLayerIds": [
    ],
    "layerOptions": 0,
    "shouldTrim": false
  },
  "frame": {
    "_class": "rect",
    "constrainProportions": false,
    "do_objectID": "0642CBF6-BA89-410F-A13A-370643C6FB49",
    "height": 16,
    "width": 102,
    "x": 0,
    "y": 0
  },
  "hasClickThrough": false,
  "hasClippingMask": false,
  "isFlippedHorizontal": false,
  "isFlippedVertical": false,
  "isLocked": false,
  "isVisible": true,
  "layerListExpandedType": 0,
  "layers": [
    {
      "class": "rectangle",
      "id": "160D7435-559D-489A-89FD-B32529B8EEE4"
    }
  ],
  "name": "Rectangle",
  "nameIsFixed": false,
  "resizingConstraint": 63,
  "resizingType": 0,
  "rotation": 0,
  "shouldBreakMaskChain": false,
  "style": {
    "_class": "style",
    "borders": [
      {
        "_class": "border",
        "color": {
          "_class": "color",
          "alpha": 1,
          "blue": 0.592,
          "green": 0.592,
          "red": 0.592
        },
        "fillType": 0,
        "isEnabled": false,
        "position": 1,
        "thickness": 1
      }
    ],
    "do_objectID": "9FFE9106-D1D8-49CD-B34E-F0FEDAE049E9",
    "endDecorationType": 0,
    "fills": [
      {
        "_class": "fill",
        "color": {
          "_class": "color",
          "alpha": 1,
          "blue": 0.6352941176470588,
          "green": 0.3019607843137255,
          "red": 0.007843137254901924
        },
        "fillType": 0,
        "isEnabled": true,
        "noiseIndex": 0,
        "noiseIntensity": 0,
        "patternFillType": 1,
        "patternTileScale": 1
      }
    ],
    "miterLimit": 10,
    "startDecorationType": 0
  },
  "windingRule": 1
}