{
  "_class": "rectangle",
  "booleanOperation": -1,
  "do_objectID": "A7279E0C-3462-4654-AE6F-9DEDAB4964C3",
  "edited": true,
  "exportOptions": {
    "_class": "exportOptions",
    "do_objectID": "DAFF87C7-043D-415E-A6F7-F997F4103EC9",
    "exportFormats": [
    ],
    "includedLayerIds": [
    ],
    "layerOptions": 0,
    "shouldTrim": false
  },
  "fixedRadius": 0,
  "frame": {
    "_class": "rect",
    "constrainProportions": false,
    "do_objectID": "02AE451C-AE75-4FA7-8AFB-577E4C41E3B5",
    "height": 1.577142857142899,
    "width": 21.99810964083177,
    "x": 0,
    "y": 0
  },
  "hasConvertedToNewRoundCorners": true,
  "isClosed": true,
  "isFlippedHorizontal": false,
  "isFlippedVertical": false,
  "isLocked": false,
  "isVisible": true,
  "layerListExpandedType": 0,
  "name": "Path",
  "nameIsFixed": false,
  "path": {
    "_class": "path",
    "isClosed": true,
    "pointRadiusBehaviour": 0,
    "points": [
      {
        "_class": "curvePoint",
        "cornerRadius": 0,
        "curveFrom": "{0.018518518518519031, 0}",
        "curveMode": 1,
        "curveTo": "{0.022192378867621619, 0.13924611831969025}",
        "hasCurveFrom": false,
        "hasCurveTo": false,
        "point": "{0.018518518518519031, 0}"
      },
      {
        "_class": "curvePoint",
        "cornerRadius": 0,
        "curveFrom": "{1.0011699465908774, 0.060811834948907739}",
        "curveMode": 1,
        "curveTo": "{1, 0}",
        "hasCurveFrom": false,
        "hasCurveTo": false,
        "point": "{1, 0}"
      },
      {
        "_class": "curvePoint",
        "cornerRadius": 0,
        "curveFrom": "{0.64232924735822716, 1}",
        "curveMode": 1,
        "curveTo": "{0.9776790538831871, 0.22747850161557492}",
        "hasCurveFrom": false,
        "hasCurveTo": false,
        "point": "{1, 1}"
      },
      {
        "_class": "curvePoint",
        "cornerRadius": 0,
        "curveFrom": "{-0.020511412178773718, 0.22257945165302395}",
        "curveMode": 1,
        "curveTo": "{0.0083185854968154983, 1}",
        "hasCurveFrom": false,
        "hasCurveTo": false,
        "point": "{0, 1}"
      }
    ]
  },
  "pointRadiusBehaviour": 0,
  "points": [
    {
      "_class": "curvePoint",
      "cornerRadius": 0,
      "curveFrom": "{0.018518518518519031, 0}",
      "curveMode": 1,
      "curveTo": "{0.022192378867621619, 0.13924611831969025}",
      "hasCurveFrom": false,
      "hasCurveTo": false,
      "point": "{0.018518518518519031, 0}"
    },
    {
      "_class": "curvePoint",
      "cornerRadius": 0,
      "curveFrom": "{1.0011699465908774, 0.060811834948907739}",
      "curveMode": 1,
      "curveTo": "{1, 0}",
      "hasCurveFrom": false,
      "hasCurveTo": false,
      "point": "{1, 0}"
    },
    {
      "_class": "curvePoint",
      "cornerRadius": 0,
      "curveFrom": "{0.64232924735822716, 1}",
      "curveMode": 1,
      "curveTo": "{0.9776790538831871, 0.22747850161557492}",
      "hasCurveFrom": false,
      "hasCurveTo": false,
      "point": "{1, 1}"
    },
    {
      "_class": "curvePoint",
      "cornerRadius": 0,
      "curveFrom": "{-0.020511412178773718, 0.22257945165302395}",
      "curveMode": 1,
      "curveTo": "{0.0083185854968154983, 1}",
      "hasCurveFrom": false,
      "hasCurveTo": false,
      "point": "{0, 1}"
    }
  ],
  "resizingConstraint": 63,
  "resizingType": 0,
  "rotation": 0,
  "shouldBreakMaskChain": false
}